skinoptics/__init__.py
skinoptics/absorption_coefficient.py
skinoptics/anisotropy_factor.py
skinoptics/colors.py
skinoptics/dataframes.py
skinoptics/refractive_index.py
skinoptics/scattering_coefficient.py
skinoptics/utils.py
skinoptics/datasets/colors/Lab_Alaluf2002.txt
skinoptics/datasets/colors/Lab_Xiao2017.txt
skinoptics/datasets/colors/Sharma2004_TableI.txt
skinoptics/datasets/colors/cmfs.txt
skinoptics/datasets/colors/rspds_A_D50_D65.txt
skinoptics/datasets/colors/rspds_C_D55_D75.txt
skinoptics/datasets/optical_properties/DE_Salomatina.txt
skinoptics/datasets/optical_properties/DE_Shimojo.txt
skinoptics/datasets/optical_properties/EP_Salomatina.txt
skinoptics/datasets/optical_properties/EP_Shimojo.txt
skinoptics/datasets/optical_properties/HY_Salomatina.txt
skinoptics/datasets/optical_properties/HY_Shimojo.txt
skinoptics/datasets/optical_properties/SCC_Salomatina.txt
skinoptics/datasets/optical_properties/beta_oxy_Friebel.txt
skinoptics/datasets/optical_properties/ext_and_molarext_eum_Sarna.txt
skinoptics/datasets/optical_properties/ext_and_molarext_oxy_and_deo_Prahl.txt
skinoptics/datasets/optical_properties/ext_and_molarext_phe_Sarna.txt
skinoptics/datasets/optical_properties/iBCC_Salomatina.txt
skinoptics/datasets/optical_properties/molarext_bil_Li.txt
skinoptics/datasets/optical_properties/mua_fat_vanVeen.txt
skinoptics/datasets/optical_properties/mua_wat_Hale.txt
skinoptics/datasets/optical_properties/mua_wat_Segelstein.txt
skinoptics/datasets/optical_properties/nBCC_Salomatina.txt
skinoptics/datasets/optical_properties/n_AT_Matiatou.txt
skinoptics/datasets/optical_properties/n_HY_Matiatou.txt
skinoptics/datasets/optical_properties/n_and_k_DE_Ding.txt
skinoptics/datasets/optical_properties/n_and_k_EP_Ding.txt
skinoptics/datasets/optical_properties/n_and_k_wat_Hale.txt
skinoptics/datasets/optical_properties/n_and_k_wat_Segelstein.txt
skinoptics/datasets/optical_properties/oxy_and_deo_Bosschaart.txt
skinoptics-0.0.8.dist-info/licenses/LICENSE.txt
skinoptics-0.0.8.dist-info/METADATA
skinoptics-0.0.8.dist-info/WHEEL
skinoptics-0.0.8.dist-info/top_level.txt
skinoptics-0.0.8.dist-info/RECORD
